README.rst
setup.py
pypicf/__init__.py
pypicf/__main__.py
pypicf/classifiers.py
pypicf/cli.py
pypicf/component.py
pypicf/core.py
pypicf/exceptions.py
pypicf/logging.py
pypicf/utils.py
pypicf.egg-info/PKG-INFO
pypicf.egg-info/SOURCES.txt
pypicf.egg-info/dependency_links.txt
pypicf.egg-info/entry_points.txt
pypicf.egg-info/requires.txt
pypicf.egg-info/top_level.txt