Metadata-Version: 1.1
Name: pypicf
Version: 1.0.0
Summary: The pypicf is an interactive tool that asks some 
Home-page: UNKNOWN
Author: Hayato Tominaga
Author-email: UNKNOWN
License: MIT License
Platform: UNKNOWN
Classifier: Development Status :: 4 - Beta
Classifier: Intended Audience :: Developers
Classifier: License :: OSI Approved :: MIT License
Classifier: Programming Language :: Python
Classifier: Programming Language :: Python :: 2 :: Only
Classifier: Programming Language :: Python :: 2.7
Classifier: Topic :: Utilities
